epal/__globals__.py
epal/__init__.py
epal/application.py
epal/config.py
epal/input.py
epal/scene.py
epal/utils.py
epal/window.py
epal/asset_manager/__init__.py
epal/asset_manager/asset.py
epal/asset_manager/asset_dumper.py
epal/asset_manager/asset_manager.py
epal/asset_manager/null_asset.png
epal/audio/__init__.py
epal/audio/audio_player.py
epal/components/__init__.py
epal/components/collider.py
epal/components/component.py
epal/components/shapes.py
epal/components/text.py
epal/components/transform.py
epal/entity/__init__.py
epal/entity/color.py
epal/entity/entity.py
epal/entity/font.py
epal-0.2.2.dist-info/licenses/LICENSE
epal-0.2.2.dist-info/METADATA
epal-0.2.2.dist-info/WHEEL
epal-0.2.2.dist-info/top_level.txt
epal-0.2.2.dist-info/RECORD
