Metadata-Version: 2.4
Name: Epal
Version: 0.2.2
Summary: Entity component system for Python
Author-email: Lucius Landschulze <lucland278@gmail.com>
License-Expression: MIT
Project-URL: Homepage, https://github.com/lucilands/Epal
Project-URL: Issues, https://github.com/lucilands/Epal/issues
Classifier: Programming Language :: Python :: 3
Classifier: Operating System :: OS Independent
Requires-Python: >=3.9
License-File: LICENSE
Requires-Dist: pygame
Dynamic: license-file
